{
    "training_progress": [
        {
            "epoch": 1,
            "train_loss": 1.6929304844865174,
            "val_loss": 1.5388783131326949,
            "val_acc": 37.76470588235294,
            "val_macro_precision": 0.37984421103270877,
            "val_macro_recall": 0.37888816233869144,
            "val_macro_f1": 0.35839035598511987,
            "val_micro_precision": 0.3776470588235294,
            "val_micro_recall": 0.3776470588235294,
            "val_micro_f1": 0.3776470588235294,
            "test_acc": 39.294117647058826,
            "test_macro_precision": 0.38324407126572707,
            "test_macro_recall": 0.3970729767024835,
            "test_macro_f1": 0.37083802360420903,
            "test_micro_precision": 0.39294117647058824,
            "test_micro_recall": 0.39294117647058824,
            "test_micro_f1": 0.39294117647058824
        },
        {
            "epoch": 2,
            "train_loss": 1.4879223865883373,
            "val_loss": 1.4178407617977686,
            "val_acc": 45.05882352941177,
            "val_macro_precision": 0.46523942323709355,
            "val_macro_recall": 0.45639659005773964,
            "val_macro_f1": 0.4493498148048877,
            "val_micro_precision": 0.4505882352941176,
            "val_micro_recall": 0.4505882352941176,
            "val_micro_f1": 0.4505882352941176,
            "test_acc": 46.23529411764706,
            "test_macro_precision": 0.47298452838947164,
            "test_macro_recall": 0.46643535519617646,
            "test_macro_f1": 0.45895961467034346,
            "test_micro_precision": 0.4623529411764706,
            "test_micro_recall": 0.4623529411764706,
            "test_micro_f1": 0.4623529411764706
        },
        {
            "epoch": 3,
            "train_loss": 1.3728160936141682,
            "val_loss": 1.3404979280063085,
            "val_acc": 48.94117647058823,
            "val_macro_precision": 0.5020584847023387,
            "val_macro_recall": 0.49451638870856757,
            "val_macro_f1": 0.486474612007786,
            "val_micro_precision": 0.4894117647058824,
            "val_micro_recall": 0.4894117647058824,
            "val_micro_f1": 0.4894117647058824,
            "test_acc": 48.8235294117647,
            "test_macro_precision": 0.48956573032616707,
            "test_macro_recall": 0.4935931961206432,
            "test_macro_f1": 0.4785969138018615,
            "test_micro_precision": 0.48823529411764705,
            "test_micro_recall": 0.48823529411764705,
            "test_micro_f1": 0.48823529411764705
        },
        {
            "epoch": 4,
            "train_loss": 1.2817556585106895,
            "val_loss": 1.3098746623311723,
            "val_acc": 50.23529411764706,
            "val_macro_precision": 0.5069900779967442,
            "val_macro_recall": 0.5058122699586761,
            "val_macro_f1": 0.4981877114113957,
            "val_micro_precision": 0.5023529411764706,
            "val_micro_recall": 0.5023529411764706,
            "val_micro_f1": 0.5023529411764706,
            "test_acc": 50.8235294117647,
            "test_macro_precision": 0.5150630680998144,
            "test_macro_recall": 0.5113044366419272,
            "test_macro_f1": 0.5021613695813402,
            "test_micro_precision": 0.508235294117647,
            "test_micro_recall": 0.508235294117647,
            "test_micro_f1": 0.508235294117647
        },
        {
            "epoch": 5,
            "train_loss": 1.1992138802448167,
            "val_loss": 1.3051044004304069,
            "val_acc": 52.0,
            "val_macro_precision": 0.5243913294518191,
            "val_macro_recall": 0.5171539554603669,
            "val_macro_f1": 0.5175992927881138,
            "val_micro_precision": 0.52,
            "val_micro_recall": 0.52,
            "val_micro_f1": 0.52,
            "test_acc": 49.529411764705884,
            "test_macro_precision": 0.498449107270331,
            "test_macro_recall": 0.49367743382470247,
            "test_macro_f1": 0.4939923453253143,
            "test_micro_precision": 0.49529411764705883,
            "test_micro_recall": 0.49529411764705883,
            "test_micro_f1": 0.49529411764705883
        },
        {
            "epoch": 6,
            "train_loss": 1.143813319852419,
            "val_loss": 1.2776195577212743,
            "val_acc": 52.11764705882353,
            "val_macro_precision": 0.5220865798756152,
            "val_macro_recall": 0.5241926737415809,
            "val_macro_f1": 0.5160719222794811,
            "val_micro_precision": 0.5211764705882352,
            "val_micro_recall": 0.5211764705882352,
            "val_micro_f1": 0.5211764705882352,
            "test_acc": 51.294117647058826,
            "test_macro_precision": 0.5099211090713005,
            "test_macro_recall": 0.5160871639113039,
            "test_macro_f1": 0.5093473401893175,
            "test_micro_precision": 0.5129411764705882,
            "test_micro_recall": 0.5129411764705882,
            "test_micro_f1": 0.5129411764705882
        },
        {
            "epoch": 7,
            "train_loss": 1.082783450590116,
            "val_loss": 1.2563934028148651,
            "val_acc": 54.11764705882353,
            "val_macro_precision": 0.5425421895972871,
            "val_macro_recall": 0.5452087963116521,
            "val_macro_f1": 0.5377201344739283,
            "val_micro_precision": 0.5411764705882353,
            "val_micro_recall": 0.5411764705882353,
            "val_micro_f1": 0.5411764705882353,
            "test_acc": 54.23529411764706,
            "test_macro_precision": 0.542848854883009,
            "test_macro_recall": 0.5480774849991077,
            "test_macro_f1": 0.5389259092286159,
            "test_micro_precision": 0.5423529411764706,
            "test_micro_recall": 0.5423529411764706,
            "test_micro_f1": 0.5423529411764706
        },
        {
            "epoch": 8,
            "train_loss": 1.005843851610879,
            "val_loss": 1.242444349186761,
            "val_acc": 56.8235294117647,
            "val_macro_precision": 0.578490157864567,
            "val_macro_recall": 0.567579039974476,
            "val_macro_f1": 0.5685961831293307,
            "val_micro_precision": 0.5682352941176471,
            "val_micro_recall": 0.5682352941176471,
            "val_micro_f1": 0.5682352941176471,
            "test_acc": 54.94117647058823,
            "test_macro_precision": 0.5631949287878784,
            "test_macro_recall": 0.5484869592136832,
            "test_macro_f1": 0.5512305336527129,
            "test_micro_precision": 0.5494117647058824,
            "test_micro_recall": 0.5494117647058824,
            "test_micro_f1": 0.5494117647058824
        },
        {
            "epoch": 9,
            "train_loss": 0.9809304720887514,
            "val_loss": 1.217608004808426,
            "val_acc": 56.8235294117647,
            "val_macro_precision": 0.569048796637521,
            "val_macro_recall": 0.5675479773211042,
            "val_macro_f1": 0.5646065447747207,
            "val_micro_precision": 0.5682352941176471,
            "val_micro_recall": 0.5682352941176471,
            "val_micro_f1": 0.5682352941176471,
            "test_acc": 53.294117647058826,
            "test_macro_precision": 0.5284214934007501,
            "test_macro_recall": 0.5332877133517288,
            "test_macro_f1": 0.5273859260933057,
            "test_micro_precision": 0.5329411764705883,
            "test_micro_recall": 0.5329411764705883,
            "test_micro_f1": 0.5329411764705883
        },
        {
            "epoch": 10,
            "train_loss": 0.9139848323625939,
            "val_loss": 1.2036695565496172,
            "val_acc": 57.64705882352941,
            "val_macro_precision": 0.5863953475627796,
            "val_macro_recall": 0.5779612053783668,
            "val_macro_f1": 0.5741660362284409,
            "val_micro_precision": 0.5764705882352941,
            "val_micro_recall": 0.5764705882352941,
            "val_micro_f1": 0.5764705882352941,
            "test_acc": 58.588235294117645,
            "test_macro_precision": 0.5869385595988265,
            "test_macro_recall": 0.589169295146276,
            "test_macro_f1": 0.5838900149267431,
            "test_micro_precision": 0.5858823529411765,
            "test_micro_recall": 0.5858823529411765,
            "test_micro_f1": 0.5858823529411765
        },
        {
            "epoch": 11,
            "train_loss": 0.8669919661272352,
            "val_loss": 1.1915717720985413,
            "val_acc": 57.76470588235294,
            "val_macro_precision": 0.579287170213031,
            "val_macro_recall": 0.5794279944002987,
            "val_macro_f1": 0.5768992765058002,
            "val_micro_precision": 0.5776470588235294,
            "val_micro_recall": 0.5776470588235294,
            "val_micro_f1": 0.5776470588235294,
            "test_acc": 56.705882352941174,
            "test_macro_precision": 0.571832467650544,
            "test_macro_recall": 0.5696501029016203,
            "test_macro_f1": 0.5694584873740941,
            "test_micro_precision": 0.5670588235294117,
            "test_micro_recall": 0.5670588235294117,
            "test_micro_f1": 0.5670588235294117
        },
        {
            "epoch": 12,
            "train_loss": 0.816630309987291,
            "val_loss": 1.2604860748563493,
            "val_acc": 56.705882352941174,
            "val_macro_precision": 0.570873350927978,
            "val_macro_recall": 0.5692006157776167,
            "val_macro_f1": 0.5634399845888451,
            "val_micro_precision": 0.5670588235294117,
            "val_micro_recall": 0.5670588235294117,
            "val_micro_f1": 0.5670588235294117,
            "test_acc": 58.11764705882353,
            "test_macro_precision": 0.5788837317080574,
            "test_macro_recall": 0.5856011702723036,
            "test_macro_f1": 0.5771545121051193,
            "test_micro_precision": 0.5811764705882353,
            "test_micro_recall": 0.5811764705882353,
            "test_micro_f1": 0.5811764705882353
        },
        {
            "epoch": 13,
            "train_loss": 0.766176620933497,
            "val_loss": 1.2553719622748238,
            "val_acc": 59.1764705882353,
            "val_macro_precision": 0.5980575165972386,
            "val_macro_recall": 0.5931343902006279,
            "val_macro_f1": 0.588693786697078,
            "val_micro_precision": 0.591764705882353,
            "val_micro_recall": 0.591764705882353,
            "val_micro_f1": 0.591764705882353,
            "test_acc": 58.8235294117647,
            "test_macro_precision": 0.5856798007263481,
            "test_macro_recall": 0.5919475599232805,
            "test_macro_f1": 0.585635653279376,
            "test_micro_precision": 0.5882352941176471,
            "test_micro_recall": 0.5882352941176471,
            "test_micro_f1": 0.5882352941176471
        },
        {
            "epoch": 14,
            "train_loss": 0.7448346837658748,
            "val_loss": 1.202053495815822,
            "val_acc": 58.8235294117647,
            "val_macro_precision": 0.5949505558582554,
            "val_macro_recall": 0.5915437454294464,
            "val_macro_f1": 0.5884446345842427,
            "val_micro_precision": 0.5882352941176471,
            "val_micro_recall": 0.5882352941176471,
            "val_micro_f1": 0.5882352941176471,
            "test_acc": 59.411764705882355,
            "test_macro_precision": 0.595978464390042,
            "test_macro_recall": 0.5970359121126975,
            "test_macro_f1": 0.594641372844149,
            "test_micro_precision": 0.5941176470588235,
            "test_micro_recall": 0.5941176470588235,
            "test_micro_f1": 0.5941176470588235
        },
        {
            "epoch": 15,
            "train_loss": 0.6815139077534186,
            "val_loss": 1.24824258685112,
            "val_acc": 60.0,
            "val_macro_precision": 0.6008490332577064,
            "val_macro_recall": 0.5991281660872693,
            "val_macro_f1": 0.5990429290502733,
            "val_micro_precision": 0.6,
            "val_micro_recall": 0.6,
            "val_micro_f1": 0.6,
            "test_acc": 58.705882352941174,
            "test_macro_precision": 0.5916523446319967,
            "test_macro_recall": 0.5887623217385398,
            "test_macro_f1": 0.5895892438988067,
            "test_micro_precision": 0.5870588235294117,
            "test_micro_recall": 0.5870588235294117,
            "test_micro_f1": 0.5870588235294117
        },
        {
            "epoch": 16,
            "train_loss": 0.6746078122442014,
            "val_loss": 1.2639482447079249,
            "val_acc": 57.294117647058826,
            "val_macro_precision": 0.5743955821468294,
            "val_macro_recall": 0.5762006373635283,
            "val_macro_f1": 0.5724141720683973,
            "val_micro_precision": 0.5729411764705883,
            "val_micro_recall": 0.5729411764705883,
            "val_micro_f1": 0.5729411764705883,
            "test_acc": 57.76470588235294,
            "test_macro_precision": 0.5768267870403093,
            "test_macro_recall": 0.5799706694844179,
            "test_macro_f1": 0.576614471179778,
            "test_micro_precision": 0.5776470588235294,
            "test_micro_recall": 0.5776470588235294,
            "test_micro_f1": 0.5776470588235294
        },
        {
            "epoch": 17,
            "train_loss": 0.6266579474801215,
            "val_loss": 1.3036715941769736,
            "val_acc": 59.05882352941177,
            "val_macro_precision": 0.5957063783673954,
            "val_macro_recall": 0.5903054511797753,
            "val_macro_f1": 0.5880442639472885,
            "val_micro_precision": 0.5905882352941176,
            "val_micro_recall": 0.5905882352941176,
            "val_micro_f1": 0.5905882352941176,
            "test_acc": 57.1764705882353,
            "test_macro_precision": 0.57682426338384,
            "test_macro_recall": 0.5740386240402825,
            "test_macro_f1": 0.5698190738590626,
            "test_micro_precision": 0.571764705882353,
            "test_micro_recall": 0.571764705882353,
            "test_micro_f1": 0.571764705882353
        },
        {
            "epoch": 18,
            "train_loss": 0.5833881761983176,
            "val_loss": 1.2703968712261744,
            "val_acc": 60.470588235294116,
            "val_macro_precision": 0.6130298885251323,
            "val_macro_recall": 0.6077885917930365,
            "val_macro_f1": 0.6044466766004101,
            "val_micro_precision": 0.6047058823529412,
            "val_micro_recall": 0.6047058823529412,
            "val_micro_f1": 0.6047058823529412,
            "test_acc": 60.94117647058823,
            "test_macro_precision": 0.6126037445220535,
            "test_macro_recall": 0.6150411948697133,
            "test_macro_f1": 0.6096515583597907,
            "test_micro_precision": 0.6094117647058823,
            "test_micro_recall": 0.6094117647058823,
            "test_micro_f1": 0.6094117647058823
        },
        {
            "epoch": 19,
            "train_loss": 0.5441053726962793,
            "val_loss": 1.3474100189549583,
            "val_acc": 57.64705882352941,
            "val_macro_precision": 0.5828682451646248,
            "val_macro_recall": 0.574741745626352,
            "val_macro_f1": 0.5717636112145682,
            "val_micro_precision": 0.5764705882352941,
            "val_micro_recall": 0.5764705882352941,
            "val_micro_f1": 0.5764705882352941,
            "test_acc": 58.588235294117645,
            "test_macro_precision": 0.5936254303854948,
            "test_macro_recall": 0.5861508212912904,
            "test_macro_f1": 0.5824047008380361,
            "test_micro_precision": 0.5858823529411765,
            "test_micro_recall": 0.5858823529411765,
            "test_micro_f1": 0.5858823529411765
        },
        {
            "epoch": 20,
            "train_loss": 0.5271097212751336,
            "val_loss": 1.3086502254009247,
            "val_acc": 60.588235294117645,
            "val_macro_precision": 0.6099529075308588,
            "val_macro_recall": 0.6051068055114625,
            "val_macro_f1": 0.6043259037424115,
            "val_micro_precision": 0.6058823529411764,
            "val_micro_recall": 0.6058823529411764,
            "val_micro_f1": 0.6058823529411764,
            "test_acc": 59.294117647058826,
            "test_macro_precision": 0.6010796957757799,
            "test_macro_recall": 0.5947797894794479,
            "test_macro_f1": 0.5960168405369172,
            "test_micro_precision": 0.5929411764705882,
            "test_micro_recall": 0.5929411764705882,
            "test_micro_f1": 0.5929411764705882
        },
        {
            "epoch": 21,
            "train_loss": 0.49654909188502305,
            "val_loss": 1.3584426939487457,
            "val_acc": 60.23529411764706,
            "val_macro_precision": 0.6135871347924057,
            "val_macro_recall": 0.6028044837623928,
            "val_macro_f1": 0.6002944649747562,
            "val_micro_precision": 0.6023529411764705,
            "val_micro_recall": 0.6023529411764705,
            "val_micro_f1": 0.6023529411764705,
            "test_acc": 60.705882352941174,
            "test_macro_precision": 0.6096284109134992,
            "test_macro_recall": 0.6088580157703513,
            "test_macro_f1": 0.6025255854999769,
            "test_micro_precision": 0.6070588235294118,
            "test_micro_recall": 0.6070588235294118,
            "test_micro_f1": 0.6070588235294118
        },
        {
            "epoch": 22,
            "train_loss": 0.45822619263813874,
            "val_loss": 1.4622268208435603,
            "val_acc": 58.588235294117645,
            "val_macro_precision": 0.5890212151120635,
            "val_macro_recall": 0.5879450843877525,
            "val_macro_f1": 0.5834500493814182,
            "val_micro_precision": 0.5858823529411765,
            "val_micro_recall": 0.5858823529411765,
            "val_micro_f1": 0.5858823529411765,
            "test_acc": 60.11764705882353,
            "test_macro_precision": 0.5977398672602364,
            "test_macro_recall": 0.6047832800793098,
            "test_macro_f1": 0.5976148781494474,
            "test_micro_precision": 0.6011764705882353,
            "test_micro_recall": 0.6011764705882353,
            "test_micro_f1": 0.6011764705882353
        },
        {
            "epoch": 23,
            "train_loss": 0.44115340779317874,
            "val_loss": 1.4183209453310286,
            "val_acc": 61.05882352941177,
            "val_macro_precision": 0.6165972377159132,
            "val_macro_recall": 0.6130011945959407,
            "val_macro_f1": 0.6083280796576593,
            "val_micro_precision": 0.6105882352941177,
            "val_micro_recall": 0.6105882352941177,
            "val_micro_f1": 0.6105882352941177,
            "test_acc": 59.529411764705884,
            "test_macro_precision": 0.6084946214734047,
            "test_macro_recall": 0.5999881803971493,
            "test_macro_f1": 0.5950231161261677,
            "test_micro_precision": 0.5952941176470589,
            "test_micro_recall": 0.5952941176470589,
            "test_micro_f1": 0.5952941176470589
        },
        {
            "epoch": 24,
            "train_loss": 0.4292732290575437,
            "val_loss": 1.4580410718917847,
            "val_acc": 60.0,
            "val_macro_precision": 0.606400507809964,
            "val_macro_recall": 0.6005835040463054,
            "val_macro_f1": 0.6001367950659323,
            "val_micro_precision": 0.6,
            "val_micro_recall": 0.6,
            "val_micro_f1": 0.6,
            "test_acc": 59.529411764705884,
            "test_macro_precision": 0.6061613618234621,
            "test_macro_recall": 0.596466781124647,
            "test_macro_f1": 0.5966844957439995,
            "test_micro_precision": 0.5952941176470589,
            "test_micro_recall": 0.5952941176470589,
            "test_micro_f1": 0.5952941176470589
        },
        {
            "epoch": 25,
            "train_loss": 0.4080137992016623,
            "val_loss": 1.478412730353219,
            "val_acc": 59.76470588235294,
            "val_macro_precision": 0.6009661093407698,
            "val_macro_recall": 0.6005062422771136,
            "val_macro_f1": 0.5980042064604679,
            "val_micro_precision": 0.5976470588235294,
            "val_micro_recall": 0.5976470588235294,
            "val_micro_f1": 0.5976470588235294,
            "test_acc": 59.411764705882355,
            "test_macro_precision": 0.5974394883509498,
            "test_macro_recall": 0.59503882041943,
            "test_macro_f1": 0.5952918892649798,
            "test_micro_precision": 0.5941176470588235,
            "test_micro_recall": 0.5941176470588235,
            "test_micro_f1": 0.5941176470588235
        },
        {
            "epoch": 26,
            "train_loss": 0.40439316588584506,
            "val_loss": 1.4400000997952052,
            "val_acc": 60.0,
            "val_macro_precision": 0.6040720863969523,
            "val_macro_recall": 0.6008000212700202,
            "val_macro_f1": 0.6000312285981851,
            "val_micro_precision": 0.6,
            "val_micro_recall": 0.6,
            "val_micro_f1": 0.6,
            "test_acc": 60.705882352941174,
            "test_macro_precision": 0.6122818104819289,
            "test_macro_recall": 0.6101804161026689,
            "test_macro_f1": 0.607166521330418,
            "test_micro_precision": 0.6070588235294118,
            "test_micro_recall": 0.6070588235294118,
            "test_micro_f1": 0.6070588235294118
        },
        {
            "epoch": 27,
            "train_loss": 0.3658286707702084,
            "val_loss": 1.4828653505870275,
            "val_acc": 60.94117647058823,
            "val_macro_precision": 0.61381360641646,
            "val_macro_recall": 0.6044683100389757,
            "val_macro_f1": 0.605362775059268,
            "val_micro_precision": 0.6094117647058823,
            "val_micro_recall": 0.6094117647058823,
            "val_micro_f1": 0.6094117647058823,
            "test_acc": 61.294117647058826,
            "test_macro_precision": 0.6225979362789511,
            "test_macro_recall": 0.6100453725333489,
            "test_macro_f1": 0.611585504673844,
            "test_micro_precision": 0.6129411764705882,
            "test_micro_recall": 0.6129411764705882,
            "test_micro_f1": 0.6129411764705882
        },
        {
            "epoch": 28,
            "train_loss": 0.34632959780849026,
            "val_loss": 1.4732480474880763,
            "val_acc": 61.294117647058826,
            "val_macro_precision": 0.6174796725014117,
            "val_macro_recall": 0.6130862220284755,
            "val_macro_f1": 0.6118337188693145,
            "val_micro_precision": 0.6129411764705882,
            "val_micro_recall": 0.6129411764705882,
            "val_micro_f1": 0.6129411764705882,
            "test_acc": 61.88235294117647,
            "test_macro_precision": 0.6218604746977193,
            "test_macro_recall": 0.6195298799033583,
            "test_macro_f1": 0.6170035451797317,
            "test_micro_precision": 0.6188235294117647,
            "test_micro_recall": 0.6188235294117647,
            "test_micro_f1": 0.6188235294117647
        },
        {
            "epoch": 29,
            "train_loss": 0.3425535529016334,
            "val_loss": 1.526697269507817,
            "val_acc": 62.35294117647059,
            "val_macro_precision": 0.6389053871947393,
            "val_macro_recall": 0.6205504723366012,
            "val_macro_f1": 0.6211321836064776,
            "val_micro_precision": 0.6235294117647059,
            "val_micro_recall": 0.6235294117647059,
            "val_micro_f1": 0.6235294117647059,
            "test_acc": 59.294117647058826,
            "test_macro_precision": 0.6021950830140484,
            "test_macro_recall": 0.5902370080452273,
            "test_macro_f1": 0.5877837639105713,
            "test_micro_precision": 0.5929411764705882,
            "test_micro_recall": 0.5929411764705882,
            "test_micro_f1": 0.5929411764705882
        },
        {
            "epoch": 30,
            "train_loss": 0.32124074569372374,
            "val_loss": 1.5007689595222473,
            "val_acc": 62.705882352941174,
            "val_macro_precision": 0.6292090420188335,
            "val_macro_recall": 0.6281702991544114,
            "val_macro_f1": 0.6252237180118411,
            "val_micro_precision": 0.6270588235294118,
            "val_micro_recall": 0.6270588235294118,
            "val_micro_f1": 0.6270588235294118,
            "test_acc": 62.35294117647059,
            "test_macro_precision": 0.6248792322231288,
            "test_macro_recall": 0.6257291168150566,
            "test_macro_f1": 0.6224146453788956,
            "test_micro_precision": 0.6235294117647059,
            "test_micro_recall": 0.6235294117647059,
            "test_micro_f1": 0.6235294117647059
        },
        {
            "epoch": 31,
            "train_loss": 0.29931594960600416,
            "val_loss": 1.6080718210765295,
            "val_acc": 59.529411764705884,
            "val_macro_precision": 0.6047629294408895,
            "val_macro_recall": 0.5948095359186937,
            "val_macro_f1": 0.5928078247818394,
            "val_micro_precision": 0.5952941176470589,
            "val_micro_recall": 0.5952941176470589,
            "val_micro_f1": 0.5952941176470589,
            "test_acc": 58.8235294117647,
            "test_macro_precision": 0.6011303889153271,
            "test_macro_recall": 0.5886961161680059,
            "test_macro_f1": 0.5890227047666744,
            "test_micro_precision": 0.5882352941176471,
            "test_micro_recall": 0.5882352941176471,
            "test_micro_f1": 0.5882352941176471
        },
        {
            "epoch": 32,
            "train_loss": 0.2926702721514434,
            "val_loss": 1.6137311969484602,
            "val_acc": 59.05882352941177,
            "val_macro_precision": 0.5923001681631567,
            "val_macro_recall": 0.5897714631088874,
            "val_macro_f1": 0.588857418126457,
            "val_micro_precision": 0.5905882352941176,
            "val_micro_recall": 0.5905882352941176,
            "val_micro_f1": 0.5905882352941176,
            "test_acc": 61.411764705882355,
            "test_macro_precision": 0.6191638130736532,
            "test_macro_recall": 0.6138180370824903,
            "test_macro_f1": 0.6143063262331229,
            "test_micro_precision": 0.6141176470588235,
            "test_micro_recall": 0.6141176470588235,
            "test_micro_f1": 0.6141176470588235
        },
        {
            "epoch": 33,
            "train_loss": 0.18013927885374734,
            "val_loss": 1.567733415535518,
            "val_acc": 61.05882352941177,
            "val_macro_precision": 0.6165963939703272,
            "val_macro_recall": 0.6111438848428467,
            "val_macro_f1": 0.6076893074292702,
            "val_micro_precision": 0.6105882352941177,
            "val_micro_recall": 0.6105882352941177,
            "val_micro_f1": 0.6105882352941177,
            "test_acc": 61.88235294117647,
            "test_macro_precision": 0.6293444514828938,
            "test_macro_recall": 0.6211551411060515,
            "test_macro_f1": 0.6172649103380801,
            "test_micro_precision": 0.6188235294117647,
            "test_micro_recall": 0.6188235294117647,
            "test_micro_f1": 0.6188235294117647
        },
        {
            "epoch": 34,
            "train_loss": 0.14721822776944837,
            "val_loss": 1.5933911204338074,
            "val_acc": 61.76470588235294,
            "val_macro_precision": 0.621603837339859,
            "val_macro_recall": 0.616832035809448,
            "val_macro_f1": 0.6167264123616789,
            "val_micro_precision": 0.6176470588235294,
            "val_micro_recall": 0.6176470588235294,
            "val_micro_f1": 0.6176470588235294,
            "test_acc": 62.470588235294116,
            "test_macro_precision": 0.6279391191017049,
            "test_macro_recall": 0.62352695896097,
            "test_macro_f1": 0.6241561148184079,
            "test_micro_precision": 0.6247058823529412,
            "test_micro_recall": 0.6247058823529412,
            "test_micro_f1": 0.6247058823529412
        },
        {
            "epoch": 35,
            "train_loss": 0.13386292934905145,
            "val_loss": 1.6214689697538103,
            "val_acc": 62.23529411764706,
            "val_macro_precision": 0.626387703290521,
            "val_macro_recall": 0.6230856323645471,
            "val_macro_f1": 0.621748696156014,
            "val_micro_precision": 0.6223529411764706,
            "val_micro_recall": 0.6223529411764706,
            "val_micro_f1": 0.6223529411764706,
            "test_acc": 63.529411764705884,
            "test_macro_precision": 0.6387566484708657,
            "test_macro_recall": 0.6357669606036053,
            "test_macro_f1": 0.6351765180572492,
            "test_micro_precision": 0.6352941176470588,
            "test_micro_recall": 0.6352941176470588,
            "test_micro_f1": 0.6352941176470588
        },
        {
            "epoch": 36,
            "train_loss": 0.1231107813802278,
            "val_loss": 1.7248888952391488,
            "val_acc": 61.529411764705884,
            "val_macro_precision": 0.6236070335922016,
            "val_macro_recall": 0.6140615366957867,
            "val_macro_f1": 0.6133439019099262,
            "val_micro_precision": 0.6152941176470588,
            "val_micro_recall": 0.6152941176470588,
            "val_micro_f1": 0.6152941176470588,
            "test_acc": 62.588235294117645,
            "test_macro_precision": 0.6358934467727799,
            "test_macro_recall": 0.627385045806884,
            "test_macro_f1": 0.6279030492996919,
            "test_micro_precision": 0.6258823529411764,
            "test_micro_recall": 0.6258823529411764,
            "test_micro_f1": 0.6258823529411764
        },
        {
            "epoch": 37,
            "train_loss": 0.11985943226195941,
            "val_loss": 1.707593364374978,
            "val_acc": 62.23529411764706,
            "val_macro_precision": 0.6256251400073027,
            "val_macro_recall": 0.6235341981386627,
            "val_macro_f1": 0.621739025579172,
            "val_micro_precision": 0.6223529411764706,
            "val_micro_recall": 0.6223529411764706,
            "val_micro_f1": 0.6223529411764706,
            "test_acc": 62.705882352941174,
            "test_macro_precision": 0.6270109487792372,
            "test_macro_recall": 0.6280547355541551,
            "test_macro_f1": 0.6266500599380443,
            "test_micro_precision": 0.6270588235294118,
            "test_micro_recall": 0.6270588235294118,
            "test_micro_f1": 0.6270588235294118
        }
    ],
    "best_model": {
        "epoch": 30
    },
    "hyperparameters": {
        "num_epochs": 1000,
        "lr": 0.0001,
        "weight_decay": 0.0001,
        "patience": 8,
        "batch_size": 64,
        "device": "cuda",
        "video_dim": 768,
        "audio_dim": 1024,
        "fused_dim": 512,
        "num_classes": 6,
        "max_seq_len": 57,
        "fusion_dropout": 0.2,
        "classifier_dropout": 0.3,
        "num_layers": 2,
        "num_heads": 8,
        "scheduler_factor": 0.3,
        "scheduler_patience": 5,
        "focal_gamma": 2.0
    }
}